{"header":{"id":2148,"city":"AUSTIN","canonical_name":"ONE-2-ONE BAR","canonical_address":"1509 S LAMAR BLVD STE 600","zip":"78704","mb_taxpayer_number":"32076333791","mb_location_number":"1","facility_ids":[],"match_score":63.75,"match_method":"mb_only","latitude":null,"longitude":null},"inspections":[],"revenue":[{"month":"2021-02-28","total_receipts":202.0,"liquor_receipts":146.0,"wine_receipts":2.0,"beer_receipts":54.0},{"month":"2021-03-31","total_receipts":6396.0,"liquor_receipts":4626.0,"wine_receipts":176.0,"beer_receipts":1594.0},{"month":"2021-04-30","total_receipts":12599.0,"liquor_receipts":7071.0,"wine_receipts":327.0,"beer_receipts":4057.0},{"month":"2021-05-31","total_receipts":24688.0,"liquor_receipts":13252.0,"wine_receipts":561.0,"beer_receipts":8263.0},{"month":"2021-06-30","total_receipts":23342.0,"liquor_receipts":13213.0,"wine_receipts":327.0,"beer_receipts":7916.0},{"month":"2021-07-31","total_receipts":27745.0,"liquor_receipts":15269.0,"wine_receipts":607.0,"beer_receipts":9944.0},{"month":"2021-08-31","total_receipts":21195.0,"liquor_receipts":12296.0,"wine_receipts":341.0,"beer_receipts":8173.0},{"month":"2021-09-30","total_receipts":18245.0,"liquor_receipts":10116.0,"wine_receipts":277.0,"beer_receipts":6597.0},{"month":"2021-10-31","total_receipts":26779.0,"liquor_receipts":12858.0,"wine_receipts":436.0,"beer_receipts":9694.0},{"month":"2021-11-30","total_receipts":22003.0,"liquor_receipts":11412.0,"wine_receipts":423.0,"beer_receipts":8049.0},{"month":"2021-12-31","total_receipts":13904.0,"liquor_receipts":8006.0,"wine_receipts":407.0,"beer_receipts":5369.0},{"month":"2022-01-31","total_receipts":0.0,"liquor_receipts":0.0,"wine_receipts":0.0,"beer_receipts":0.0},{"month":"2022-02-28","total_receipts":0.0,"liquor_receipts":0.0,"wine_receipts":0.0,"beer_receipts":0.0},{"month":"2022-03-31","total_receipts":27745.0,"liquor_receipts":0.0,"wine_receipts":0.0,"beer_receipts":0.0},{"month":"2022-04-30","total_receipts":27745.0,"liquor_receipts":0.0,"wine_receipts":0.0,"beer_receipts":0.0},{"month":"2022-05-31","total_receipts":27745.0,"liquor_receipts":0.0,"wine_receipts":0.0,"beer_receipts":0.0},{"month":"2022-06-30","total_receipts":27745.0,"liquor_receipts":0.0,"wine_receipts":0.0,"beer_receipts":0.0},{"month":"2022-07-31","total_receipts":27745.0,"liquor_receipts":0.0,"wine_receipts":0.0,"beer_receipts":0.0},{"month":"2022-08-31","total_receipts":27745.0,"liquor_receipts":0.0,"wine_receipts":0.0,"beer_receipts":0.0},{"month":"2022-09-30","total_receipts":27744.0,"liquor_receipts":0.0,"wine_receipts":0.0,"beer_receipts":0.0},{"month":"2022-10-31","total_receipts":27744.0,"liquor_receipts":0.0,"wine_receipts":0.0,"beer_receipts":0.0},{"month":"2022-11-30","total_receipts":13872.0,"liquor_receipts":13872.0,"wine_receipts":0.0,"beer_receipts":0.0},{"month":"2022-12-31","total_receipts":27744.0,"liquor_receipts":0.0,"wine_receipts":0.0,"beer_receipts":0.0},{"month":"2023-01-31","total_receipts":27744.0,"liquor_receipts":0.0,"wine_receipts":0.0,"beer_receipts":0.0},{"month":"2023-02-28","total_receipts":27744.0,"liquor_receipts":0.0,"wine_receipts":0.0,"beer_receipts":0.0}],"violations":[]}