{"header":{"id":2226,"city":"AUSTIN","canonical_name":"SKY","canonical_address":"214 BARTON SPRINGS RD STE 1922","zip":"78704","mb_taxpayer_number":"32060200949","mb_location_number":"1","facility_ids":[],"match_score":54.22,"match_method":"mb_only","latitude":null,"longitude":null},"inspections":[],"revenue":[{"month":"2016-06-30","total_receipts":2343.0,"liquor_receipts":1414.0,"wine_receipts":711.0,"beer_receipts":218.0},{"month":"2016-07-31","total_receipts":11769.0,"liquor_receipts":6562.0,"wine_receipts":3836.0,"beer_receipts":1371.0},{"month":"2016-08-31","total_receipts":10883.0,"liquor_receipts":6461.0,"wine_receipts":3325.0,"beer_receipts":1097.0},{"month":"2016-09-30","total_receipts":11740.0,"liquor_receipts":6344.0,"wine_receipts":3970.0,"beer_receipts":1426.0},{"month":"2016-10-31","total_receipts":14857.0,"liquor_receipts":8190.0,"wine_receipts":5108.0,"beer_receipts":1559.0},{"month":"2016-11-30","total_receipts":12999.0,"liquor_receipts":6823.0,"wine_receipts":4531.0,"beer_receipts":1645.0},{"month":"2016-12-31","total_receipts":11111.0,"liquor_receipts":5967.0,"wine_receipts":3743.0,"beer_receipts":1401.0},{"month":"2017-01-31","total_receipts":13100.0,"liquor_receipts":6661.0,"wine_receipts":4783.0,"beer_receipts":1656.0},{"month":"2017-02-28","total_receipts":13657.0,"liquor_receipts":7141.0,"wine_receipts":4807.0,"beer_receipts":1709.0},{"month":"2017-03-31","total_receipts":16814.0,"liquor_receipts":9391.0,"wine_receipts":5731.0,"beer_receipts":1692.0},{"month":"2017-04-30","total_receipts":13156.0,"liquor_receipts":7873.0,"wine_receipts":3580.0,"beer_receipts":1703.0},{"month":"2017-05-31","total_receipts":15850.0,"liquor_receipts":9527.0,"wine_receipts":4384.0,"beer_receipts":1939.0},{"month":"2017-06-30","total_receipts":17078.0,"liquor_receipts":10083.0,"wine_receipts":4630.0,"beer_receipts":2365.0},{"month":"2017-07-31","total_receipts":18422.0,"liquor_receipts":11314.0,"wine_receipts":4844.0,"beer_receipts":2264.0},{"month":"2017-08-31","total_receipts":19105.0,"liquor_receipts":11952.0,"wine_receipts":4512.0,"beer_receipts":2641.0},{"month":"2017-09-30","total_receipts":16181.0,"liquor_receipts":9519.0,"wine_receipts":4476.0,"beer_receipts":2186.0},{"month":"2017-10-31","total_receipts":18762.0,"liquor_receipts":10831.0,"wine_receipts":5299.0,"beer_receipts":2632.0},{"month":"2017-11-30","total_receipts":15206.0,"liquor_receipts":7654.0,"wine_receipts":5183.0,"beer_receipts":2369.0},{"month":"2017-12-31","total_receipts":17048.0,"liquor_receipts":9543.0,"wine_receipts":5201.0,"beer_receipts":2304.0},{"month":"2018-01-31","total_receipts":14359.0,"liquor_receipts":8021.0,"wine_receipts":4457.0,"beer_receipts":1881.0},{"month":"2018-02-28","total_receipts":18870.0,"liquor_receipts":11167.0,"wine_receipts":5113.0,"beer_receipts":2590.0},{"month":"2018-03-31","total_receipts":27844.0,"liquor_receipts":15523.0,"wine_receipts":9036.0,"beer_receipts":3285.0},{"month":"2018-04-30","total_receipts":23696.0,"liquor_receipts":14100.0,"wine_receipts":6140.0,"beer_receipts":3456.0},{"month":"2018-05-31","total_receipts":22428.0,"liquor_receipts":14352.0,"wine_receipts":5340.0,"beer_receipts":2736.0},{"month":"2018-06-30","total_receipts":24343.0,"liquor_receipts":14691.0,"wine_receipts":7043.0,"beer_receipts":2609.0},{"month":"2018-07-31","total_receipts":24183.0,"liquor_receipts":15182.0,"wine_receipts":6112.0,"beer_receipts":2889.0},{"month":"2018-08-31","total_receipts":23705.0,"liquor_receipts":13976.0,"wine_receipts":6250.0,"beer_receipts":3479.0},{"month":"2018-09-30","total_receipts":24571.0,"liquor_receipts":15493.0,"wine_receipts":5813.0,"beer_receipts":3265.0},{"month":"2018-10-31","total_receipts":19659.0,"liquor_receipts":11002.0,"wine_receipts":5555.0,"beer_receipts":3102.0},{"month":"2018-11-30","total_receipts":22228.0,"liquor_receipts":12846.0,"wine_receipts":7339.0,"beer_receipts":2043.0},{"month":"2018-12-31","total_receipts":25876.0,"liquor_receipts":14281.0,"wine_receipts":7898.0,"beer_receipts":3697.0},{"month":"2019-01-31","total_receipts":17746.0,"liquor_receipts":10114.0,"wine_receipts":5542.0,"beer_receipts":2090.0},{"month":"2019-02-28","total_receipts":23355.0,"liquor_receipts":14576.0,"wine_receipts":5996.0,"beer_receipts":2783.0},{"month":"2019-03-31","total_receipts":27002.0,"liquor_receipts":16297.0,"wine_receipts":6792.0,"beer_receipts":3913.0},{"month":"2019-04-30","total_receipts":22392.0,"liquor_receipts":13314.0,"wine_receipts":6171.0,"beer_receipts":2907.0},{"month":"2019-05-31","total_receipts":23216.0,"liquor_receipts":13970.0,"wine_receipts":6000.0,"beer_receipts":3246.0},{"month":"2019-06-30","total_receipts":25165.0,"liquor_receipts":15463.0,"wine_receipts":6425.0,"beer_receipts":3277.0},{"month":"2019-07-31","total_receipts":21399.0,"liquor_receipts":12722.0,"wine_receipts":5904.0,"beer_receipts":2773.0},{"month":"2019-08-31","total_receipts":18976.0,"liquor_receipts":11157.0,"wine_receipts":4877.0,"beer_receipts":2942.0},{"month":"2019-09-30","total_receipts":20528.0,"liquor_receipts":12509.0,"wine_receipts":5112.0,"beer_receipts":2907.0},{"month":"2019-10-31","total_receipts":21097.0,"liquor_receipts":12672.0,"wine_receipts":5072.0,"beer_receipts":3353.0},{"month":"2019-11-30","total_receipts":17548.0,"liquor_receipts":10038.0,"wine_receipts":5174.0,"beer_receipts":2336.0},{"month":"2019-12-31","total_receipts":18651.0,"liquor_receipts":11144.0,"wine_receipts":4865.0,"beer_receipts":2642.0},{"month":"2020-01-31","total_receipts":14357.0,"liquor_receipts":8281.0,"wine_receipts":4283.0,"beer_receipts":1793.0},{"month":"2020-02-29","total_receipts":18284.0,"liquor_receipts":10036.0,"wine_receipts":5766.0,"beer_receipts":2482.0},{"month":"2020-03-31","total_receipts":8890.0,"liquor_receipts":4884.0,"wine_receipts":2516.0,"beer_receipts":1490.0},{"month":"2020-04-30","total_receipts":0.0,"liquor_receipts":0.0,"wine_receipts":0.0,"beer_receipts":0.0},{"month":"2020-05-31","total_receipts":0.0,"liquor_receipts":0.0,"wine_receipts":0.0,"beer_receipts":0.0},{"month":"2020-06-30","total_receipts":14481.0,"liquor_receipts":7618.0,"wine_receipts":4552.0,"beer_receipts":2311.0},{"month":"2020-07-31","total_receipts":0.0,"liquor_receipts":0.0,"wine_receipts":0.0,"beer_receipts":0.0},{"month":"2020-08-31","total_receipts":0.0,"liquor_receipts":0.0,"wine_receipts":0.0,"beer_receipts":0.0},{"month":"2020-09-30","total_receipts":0.0,"liquor_receipts":0.0,"wine_receipts":0.0,"beer_receipts":0.0},{"month":"2020-10-31","total_receipts":0.0,"liquor_receipts":0.0,"wine_receipts":0.0,"beer_receipts":0.0},{"month":"2020-11-30","total_receipts":0.0,"liquor_receipts":0.0,"wine_receipts":0.0,"beer_receipts":0.0},{"month":"2020-12-31","total_receipts":0.0,"liquor_receipts":0.0,"wine_receipts":0.0,"beer_receipts":0.0},{"month":"2021-01-31","total_receipts":0.0,"liquor_receipts":0.0,"wine_receipts":0.0,"beer_receipts":0.0},{"month":"2021-02-28","total_receipts":0.0,"liquor_receipts":0.0,"wine_receipts":0.0,"beer_receipts":0.0},{"month":"2021-03-31","total_receipts":16124.0,"liquor_receipts":9986.0,"wine_receipts":3187.0,"beer_receipts":2951.0},{"month":"2021-04-30","total_receipts":21017.0,"liquor_receipts":12296.0,"wine_receipts":5490.0,"beer_receipts":3231.0},{"month":"2021-05-31","total_receipts":26649.0,"liquor_receipts":16197.0,"wine_receipts":6382.0,"beer_receipts":4070.0},{"month":"2021-06-30","total_receipts":21039.0,"liquor_receipts":12726.0,"wine_receipts":5006.0,"beer_receipts":3307.0},{"month":"2021-07-31","total_receipts":26011.0,"liquor_receipts":17086.0,"wine_receipts":5762.0,"beer_receipts":3163.0},{"month":"2021-08-31","total_receipts":21060.0,"liquor_receipts":12362.0,"wine_receipts":5886.0,"beer_receipts":2812.0},{"month":"2021-09-30","total_receipts":18122.0,"liquor_receipts":11877.0,"wine_receipts":4433.0,"beer_receipts":1812.0},{"month":"2021-10-31","total_receipts":19788.0,"liquor_receipts":12747.0,"wine_receipts":4371.0,"beer_receipts":2670.0},{"month":"2021-11-30","total_receipts":18897.0,"liquor_receipts":12372.0,"wine_receipts":4376.0,"beer_receipts":2149.0},{"month":"2021-12-31","total_receipts":22502.0,"liquor_receipts":14440.0,"wine_receipts":5130.0,"beer_receipts":2932.0},{"month":"2022-01-31","total_receipts":15596.0,"liquor_receipts":10291.0,"wine_receipts":3549.0,"beer_receipts":1756.0},{"month":"2022-02-28","total_receipts":22993.0,"liquor_receipts":15189.0,"wine_receipts":4991.0,"beer_receipts":2813.0},{"month":"2022-03-31","total_receipts":24627.0,"liquor_receipts":15001.0,"wine_receipts":5787.0,"beer_receipts":3839.0},{"month":"2022-04-30","total_receipts":29532.0,"liquor_receipts":20638.0,"wine_receipts":5138.0,"beer_receipts":3756.0},{"month":"2022-05-31","total_receipts":35637.0,"liquor_receipts":24401.0,"wine_receipts":6743.0,"beer_receipts":4493.0},{"month":"2022-06-30","total_receipts":24267.0,"liquor_receipts":15005.0,"wine_receipts":5162.0,"beer_receipts":4100.0},{"month":"2022-07-31","total_receipts":25256.0,"liquor_receipts":16629.0,"wine_receipts":5075.0,"beer_receipts":3552.0},{"month":"2022-08-31","total_receipts":21323.0,"liquor_receipts":14213.0,"wine_receipts":4785.0,"beer_receipts":2325.0},{"month":"2022-09-30","total_receipts":13721.0,"liquor_receipts":8476.0,"wine_receipts":3138.0,"beer_receipts":2107.0},{"month":"2022-10-31","total_receipts":25673.0,"liquor_receipts":16815.0,"wine_receipts":5472.0,"beer_receipts":3386.0},{"month":"2022-11-30","total_receipts":18692.0,"liquor_receipts":12884.0,"wine_receipts":3640.0,"beer_receipts":2168.0},{"month":"2022-12-31","total_receipts":27283.0,"liquor_receipts":20346.0,"wine_receipts":4602.0,"beer_receipts":2335.0},{"month":"2023-01-31","total_receipts":23476.0,"liquor_receipts":17064.0,"wine_receipts":3454.0,"beer_receipts":2958.0},{"month":"2023-02-28","total_receipts":24539.0,"liquor_receipts":16953.0,"wine_receipts":3604.0,"beer_receipts":3982.0},{"month":"2023-03-31","total_receipts":27283.0,"liquor_receipts":20346.0,"wine_receipts":4602.0,"beer_receipts":2335.0},{"month":"2023-04-30","total_receipts":28875.0,"liquor_receipts":17777.0,"wine_receipts":6184.0,"beer_receipts":4914.0},{"month":"2023-05-31","total_receipts":24901.0,"liquor_receipts":16842.0,"wine_receipts":4834.0,"beer_receipts":3225.0},{"month":"2023-06-30","total_receipts":21732.0,"liquor_receipts":15465.0,"wine_receipts":3734.0,"beer_receipts":2533.0},{"month":"2023-07-31","total_receipts":20998.0,"liquor_receipts":15950.0,"wine_receipts":2925.0,"beer_receipts":2123.0},{"month":"2023-08-31","total_receipts":17631.0,"liquor_receipts":11700.0,"wine_receipts":3156.0,"beer_receipts":2775.0},{"month":"2023-09-30","total_receipts":19719.0,"liquor_receipts":13290.0,"wine_receipts":3149.0,"beer_receipts":3280.0},{"month":"2023-10-31","total_receipts":20845.0,"liquor_receipts":13954.0,"wine_receipts":3383.0,"beer_receipts":3508.0},{"month":"2023-11-30","total_receipts":18521.0,"liquor_receipts":12599.0,"wine_receipts":3905.0,"beer_receipts":2017.0},{"month":"2023-12-31","total_receipts":17762.0,"liquor_receipts":12591.0,"wine_receipts":3210.0,"beer_receipts":1961.0},{"month":"2024-01-31","total_receipts":15193.0,"liquor_receipts":10168.0,"wine_receipts":2834.0,"beer_receipts":2191.0},{"month":"2024-02-29","total_receipts":19921.0,"liquor_receipts":13584.0,"wine_receipts":3553.0,"beer_receipts":2784.0},{"month":"2024-03-31","total_receipts":25563.0,"liquor_receipts":17047.0,"wine_receipts":3514.0,"beer_receipts":5002.0},{"month":"2024-04-30","total_receipts":23266.0,"liquor_receipts":15703.0,"wine_receipts":3753.0,"beer_receipts":3810.0},{"month":"2024-05-31","total_receipts":21967.0,"liquor_receipts":14458.0,"wine_receipts":3555.0,"beer_receipts":3954.0},{"month":"2024-06-30","total_receipts":19738.0,"liquor_receipts":12893.0,"wine_receipts":3004.0,"beer_receipts":3841.0},{"month":"2024-07-31","total_receipts":20235.0,"liquor_receipts":13742.0,"wine_receipts":2740.0,"beer_receipts":3753.0},{"month":"2024-08-31","total_receipts":16544.0,"liquor_receipts":11263.0,"wine_receipts":2619.0,"beer_receipts":2662.0},{"month":"2024-09-30","total_receipts":13456.0,"liquor_receipts":8400.0,"wine_receipts":2526.0,"beer_receipts":2530.0},{"month":"2024-10-31","total_receipts":19636.0,"liquor_receipts":12395.0,"wine_receipts":4219.0,"beer_receipts":3022.0},{"month":"2024-11-30","total_receipts":16206.0,"liquor_receipts":10843.0,"wine_receipts":3807.0,"beer_receipts":1556.0},{"month":"2024-12-31","total_receipts":17479.0,"liquor_receipts":11789.0,"wine_receipts":3518.0,"beer_receipts":2172.0},{"month":"2025-01-31","total_receipts":14092.0,"liquor_receipts":9262.0,"wine_receipts":3107.0,"beer_receipts":1723.0},{"month":"2025-02-28","total_receipts":14874.0,"liquor_receipts":9996.0,"wine_receipts":2301.0,"beer_receipts":2577.0},{"month":"2025-03-31","total_receipts":16592.0,"liquor_receipts":11044.0,"wine_receipts":3056.0,"beer_receipts":2492.0},{"month":"2025-04-30","total_receipts":16065.0,"liquor_receipts":10803.0,"wine_receipts":3085.0,"beer_receipts":2177.0},{"month":"2025-05-31","total_receipts":16025.0,"liquor_receipts":11110.0,"wine_receipts":3050.0,"beer_receipts":1865.0},{"month":"2025-06-30","total_receipts":11195.0,"liquor_receipts":7715.0,"wine_receipts":2013.0,"beer_receipts":1467.0},{"month":"2025-07-31","total_receipts":14365.0,"liquor_receipts":9892.0,"wine_receipts":2742.0,"beer_receipts":1731.0},{"month":"2025-08-31","total_receipts":15649.0,"liquor_receipts":10062.0,"wine_receipts":3303.0,"beer_receipts":2284.0},{"month":"2025-09-30","total_receipts":11269.0,"liquor_receipts":7456.0,"wine_receipts":2296.0,"beer_receipts":1517.0},{"month":"2025-10-31","total_receipts":14457.0,"liquor_receipts":8847.0,"wine_receipts":4010.0,"beer_receipts":1600.0},{"month":"2025-11-30","total_receipts":11167.0,"liquor_receipts":6838.0,"wine_receipts":2749.0,"beer_receipts":1580.0},{"month":"2025-12-31","total_receipts":12037.0,"liquor_receipts":8209.0,"wine_receipts":2287.0,"beer_receipts":1541.0},{"month":"2026-01-31","total_receipts":12258.0,"liquor_receipts":7988.0,"wine_receipts":2079.0,"beer_receipts":2191.0},{"month":"2026-02-28","total_receipts":10774.0,"liquor_receipts":7312.0,"wine_receipts":1555.0,"beer_receipts":1907.0},{"month":"2026-03-31","total_receipts":18451.0,"liquor_receipts":12859.0,"wine_receipts":2082.0,"beer_receipts":3510.0}],"violations":[]}