{"header":{"id":4483,"city":"AUSTIN","canonical_name":"JESTER KING CRAFT BREWERY","canonical_address":"13005 FITZHUGH RD BLDG B","zip":"78736","mb_taxpayer_number":"32036999178","mb_location_number":"1","facility_ids":[],"match_score":46.48,"match_method":"mb_only","latitude":null,"longitude":null},"inspections":[],"revenue":[{"month":"2021-06-30","total_receipts":0.0,"liquor_receipts":0.0,"wine_receipts":0.0,"beer_receipts":0.0},{"month":"2021-07-31","total_receipts":0.0,"liquor_receipts":0.0,"wine_receipts":0.0,"beer_receipts":0.0},{"month":"2021-08-31","total_receipts":0.0,"liquor_receipts":0.0,"wine_receipts":0.0,"beer_receipts":0.0},{"month":"2021-09-30","total_receipts":0.0,"liquor_receipts":0.0,"wine_receipts":0.0,"beer_receipts":0.0},{"month":"2021-10-31","total_receipts":0.0,"liquor_receipts":0.0,"wine_receipts":0.0,"beer_receipts":0.0},{"month":"2021-11-30","total_receipts":0.0,"liquor_receipts":0.0,"wine_receipts":0.0,"beer_receipts":0.0},{"month":"2021-12-31","total_receipts":0.0,"liquor_receipts":0.0,"wine_receipts":0.0,"beer_receipts":0.0},{"month":"2022-01-31","total_receipts":4521.0,"liquor_receipts":4521.0,"wine_receipts":0.0,"beer_receipts":0.0},{"month":"2022-02-28","total_receipts":1436.0,"liquor_receipts":1436.0,"wine_receipts":0.0,"beer_receipts":0.0},{"month":"2022-03-31","total_receipts":9382.0,"liquor_receipts":9382.0,"wine_receipts":0.0,"beer_receipts":0.0},{"month":"2022-04-30","total_receipts":14163.0,"liquor_receipts":14163.0,"wine_receipts":0.0,"beer_receipts":0.0},{"month":"2022-05-31","total_receipts":9813.0,"liquor_receipts":9813.0,"wine_receipts":0.0,"beer_receipts":0.0},{"month":"2022-06-30","total_receipts":12032.0,"liquor_receipts":12032.0,"wine_receipts":0.0,"beer_receipts":0.0},{"month":"2022-07-31","total_receipts":17787.0,"liquor_receipts":17787.0,"wine_receipts":0.0,"beer_receipts":0.0},{"month":"2022-08-31","total_receipts":15020.0,"liquor_receipts":15020.0,"wine_receipts":0.0,"beer_receipts":0.0},{"month":"2022-09-30","total_receipts":20829.0,"liquor_receipts":20829.0,"wine_receipts":0.0,"beer_receipts":0.0},{"month":"2022-10-31","total_receipts":21831.0,"liquor_receipts":21831.0,"wine_receipts":0.0,"beer_receipts":0.0},{"month":"2022-11-30","total_receipts":11975.0,"liquor_receipts":11975.0,"wine_receipts":0.0,"beer_receipts":0.0},{"month":"2022-12-31","total_receipts":16849.0,"liquor_receipts":16849.0,"wine_receipts":0.0,"beer_receipts":0.0},{"month":"2023-01-31","total_receipts":17592.0,"liquor_receipts":17592.0,"wine_receipts":0.0,"beer_receipts":0.0},{"month":"2023-02-28","total_receipts":15972.0,"liquor_receipts":15972.0,"wine_receipts":0.0,"beer_receipts":0.0},{"month":"2023-03-31","total_receipts":21865.0,"liquor_receipts":21865.0,"wine_receipts":0.0,"beer_receipts":0.0},{"month":"2023-04-30","total_receipts":27117.0,"liquor_receipts":27117.0,"wine_receipts":0.0,"beer_receipts":0.0},{"month":"2023-05-31","total_receipts":26775.0,"liquor_receipts":26775.0,"wine_receipts":0.0,"beer_receipts":0.0},{"month":"2023-06-30","total_receipts":20037.0,"liquor_receipts":20037.0,"wine_receipts":0.0,"beer_receipts":0.0},{"month":"2023-07-31","total_receipts":10988.0,"liquor_receipts":10988.0,"wine_receipts":0.0,"beer_receipts":0.0},{"month":"2023-08-31","total_receipts":11620.0,"liquor_receipts":11620.0,"wine_receipts":0.0,"beer_receipts":0.0},{"month":"2023-09-30","total_receipts":10362.0,"liquor_receipts":10362.0,"wine_receipts":0.0,"beer_receipts":0.0},{"month":"2023-10-31","total_receipts":6219.0,"liquor_receipts":6219.0,"wine_receipts":0.0,"beer_receipts":0.0},{"month":"2023-11-30","total_receipts":4918.0,"liquor_receipts":4918.0,"wine_receipts":0.0,"beer_receipts":0.0},{"month":"2023-12-31","total_receipts":5765.0,"liquor_receipts":5765.0,"wine_receipts":0.0,"beer_receipts":0.0},{"month":"2024-01-31","total_receipts":7095.0,"liquor_receipts":7095.0,"wine_receipts":0.0,"beer_receipts":0.0},{"month":"2024-02-29","total_receipts":8409.0,"liquor_receipts":8409.0,"wine_receipts":0.0,"beer_receipts":0.0},{"month":"2024-03-31","total_receipts":19264.0,"liquor_receipts":19264.0,"wine_receipts":0.0,"beer_receipts":0.0},{"month":"2024-04-30","total_receipts":15150.0,"liquor_receipts":15150.0,"wine_receipts":0.0,"beer_receipts":0.0},{"month":"2024-05-31","total_receipts":10013.0,"liquor_receipts":10013.0,"wine_receipts":0.0,"beer_receipts":0.0},{"month":"2024-06-30","total_receipts":7295.0,"liquor_receipts":7295.0,"wine_receipts":0.0,"beer_receipts":0.0},{"month":"2024-07-31","total_receipts":4676.0,"liquor_receipts":4676.0,"wine_receipts":0.0,"beer_receipts":0.0},{"month":"2024-08-31","total_receipts":4676.0,"liquor_receipts":4676.0,"wine_receipts":0.0,"beer_receipts":0.0},{"month":"2024-09-30","total_receipts":7657.0,"liquor_receipts":7657.0,"wine_receipts":0.0,"beer_receipts":0.0},{"month":"2024-10-31","total_receipts":9118.0,"liquor_receipts":9118.0,"wine_receipts":0.0,"beer_receipts":0.0},{"month":"2024-11-30","total_receipts":7642.0,"liquor_receipts":7642.0,"wine_receipts":0.0,"beer_receipts":0.0},{"month":"2024-12-31","total_receipts":4727.0,"liquor_receipts":4727.0,"wine_receipts":0.0,"beer_receipts":0.0},{"month":"2025-01-31","total_receipts":2729.0,"liquor_receipts":2729.0,"wine_receipts":0.0,"beer_receipts":0.0},{"month":"2025-02-28","total_receipts":3474.0,"liquor_receipts":3474.0,"wine_receipts":0.0,"beer_receipts":0.0},{"month":"2025-03-31","total_receipts":10534.0,"liquor_receipts":10534.0,"wine_receipts":0.0,"beer_receipts":0.0},{"month":"2025-04-30","total_receipts":8893.0,"liquor_receipts":8893.0,"wine_receipts":0.0,"beer_receipts":0.0},{"month":"2025-05-31","total_receipts":4151.0,"liquor_receipts":4151.0,"wine_receipts":0.0,"beer_receipts":0.0},{"month":"2025-06-30","total_receipts":4151.0,"liquor_receipts":4151.0,"wine_receipts":0.0,"beer_receipts":0.0},{"month":"2025-07-31","total_receipts":3235.0,"liquor_receipts":3235.0,"wine_receipts":0.0,"beer_receipts":0.0},{"month":"2025-08-31","total_receipts":4267.0,"liquor_receipts":4267.0,"wine_receipts":0.0,"beer_receipts":0.0},{"month":"2025-09-30","total_receipts":4439.0,"liquor_receipts":4439.0,"wine_receipts":0.0,"beer_receipts":0.0},{"month":"2025-10-31","total_receipts":6219.0,"liquor_receipts":6219.0,"wine_receipts":0.0,"beer_receipts":0.0},{"month":"2025-11-30","total_receipts":7590.0,"liquor_receipts":7590.0,"wine_receipts":0.0,"beer_receipts":0.0},{"month":"2025-12-31","total_receipts":4424.0,"liquor_receipts":4424.0,"wine_receipts":0.0,"beer_receipts":0.0},{"month":"2026-01-31","total_receipts":3701.0,"liquor_receipts":3701.0,"wine_receipts":0.0,"beer_receipts":0.0},{"month":"2026-02-28","total_receipts":3335.0,"liquor_receipts":3335.0,"wine_receipts":0.0,"beer_receipts":0.0}],"violations":[]}