{"header":{"id":5756,"city":"AUSTIN","canonical_name":"St. Stephens School","canonical_address":"6500 Saint Stephens Dr Austin","zip":"78746","mb_taxpayer_number":null,"mb_location_number":null,"facility_ids":["2800677"],"match_score":0.0,"match_method":"inspection_only","latitude":null,"longitude":null},"inspections":[{"inspection_date":"2023-05-03","score":90.0,"inspection_type":"Routine Inspection"},{"inspection_date":"2023-11-29","score":92.0,"inspection_type":"Routine Inspection"},{"inspection_date":"2024-03-21","score":96.0,"inspection_type":"Routine Inspection"},{"inspection_date":"2024-10-01","score":93.0,"inspection_type":"Routine Inspection"},{"inspection_date":"2025-11-20","score":93.0,"inspection_type":"Routine Inspection"}],"revenue":[],"violations":[],"licenses":[]}