{"header":{"id":7939,"city":"AUSTIN","canonical_name":"Mi Pueblito Food Mart","canonical_address":"8237  RESEARCH NB BLVD AUSTIN","zip":"78758","mb_taxpayer_number":null,"mb_location_number":null,"facility_ids":["12393232"],"match_score":0.0,"match_method":"inspection_only","latitude":null,"longitude":null},"inspections":[{"inspection_date":"2024-12-31","score":89.0,"inspection_type":"Routine Inspection"},{"inspection_date":"2025-06-30","score":93.0,"inspection_type":"Routine Inspection"},{"inspection_date":"2026-02-09","score":94.0,"inspection_type":"Routine Inspection"}],"revenue":[],"violations":[],"licenses":[{"license_id":"105533096.0","license_type":"BQ","tier":"Retail","primary_status":"Active","original_issue_date":"2018-01-24","current_issued_date":"2026-01-21","expiration_date":"2028-01-23","status_change_date":"2026-01-21","gun_sign":"BLUE","master_file_id":"2100023161.0","owner":"ZYNA & AARAM LLC"}]}