{"header":{"id":949,"city":"AUSTIN","canonical_name":"CASA CHAPALA MEXICAN GRILL","canonical_address":"101 SAN JACINTO BLVD","zip":"78701","mb_taxpayer_number":"17109961551","mb_location_number":"2","facility_ids":[],"match_score":59.56,"match_method":"mb_only","latitude":null,"longitude":null},"inspections":[],"revenue":[{"month":"2010-03-31","total_receipts":19403.0,"liquor_receipts":14104.0,"wine_receipts":835.0,"beer_receipts":4464.0},{"month":"2010-04-30","total_receipts":20561.0,"liquor_receipts":15327.0,"wine_receipts":1044.0,"beer_receipts":4190.0},{"month":"2010-05-31","total_receipts":24180.0,"liquor_receipts":18615.0,"wine_receipts":905.0,"beer_receipts":4660.0},{"month":"2010-06-30","total_receipts":16523.0,"liquor_receipts":12645.0,"wine_receipts":509.0,"beer_receipts":3369.0},{"month":"2010-07-31","total_receipts":21795.0,"liquor_receipts":16795.0,"wine_receipts":972.0,"beer_receipts":4028.0},{"month":"2010-08-31","total_receipts":21104.0,"liquor_receipts":16065.0,"wine_receipts":793.0,"beer_receipts":4246.0},{"month":"2010-09-30","total_receipts":20872.0,"liquor_receipts":16038.0,"wine_receipts":921.0,"beer_receipts":3913.0},{"month":"2010-10-31","total_receipts":19987.0,"liquor_receipts":14802.0,"wine_receipts":833.0,"beer_receipts":4352.0},{"month":"2010-11-30","total_receipts":19197.0,"liquor_receipts":13291.0,"wine_receipts":1288.0,"beer_receipts":4618.0},{"month":"2010-12-31","total_receipts":17402.0,"liquor_receipts":12639.0,"wine_receipts":935.0,"beer_receipts":3828.0},{"month":"2011-01-31","total_receipts":19716.0,"liquor_receipts":14526.0,"wine_receipts":852.0,"beer_receipts":4338.0},{"month":"2011-02-28","total_receipts":21839.0,"liquor_receipts":16179.0,"wine_receipts":1017.0,"beer_receipts":4643.0},{"month":"2011-03-31","total_receipts":43330.0,"liquor_receipts":32655.0,"wine_receipts":2479.0,"beer_receipts":8196.0},{"month":"2011-04-30","total_receipts":26305.0,"liquor_receipts":19551.0,"wine_receipts":1669.0,"beer_receipts":5085.0},{"month":"2011-05-31","total_receipts":19385.0,"liquor_receipts":14358.0,"wine_receipts":1108.0,"beer_receipts":3919.0},{"month":"2011-06-30","total_receipts":21327.0,"liquor_receipts":15879.0,"wine_receipts":1455.0,"beer_receipts":3993.0},{"month":"2011-07-31","total_receipts":24020.0,"liquor_receipts":17993.0,"wine_receipts":1412.0,"beer_receipts":4615.0},{"month":"2011-08-31","total_receipts":25471.0,"liquor_receipts":19924.0,"wine_receipts":4081.0,"beer_receipts":1466.0},{"month":"2011-09-30","total_receipts":22548.0,"liquor_receipts":16685.0,"wine_receipts":1697.0,"beer_receipts":4166.0},{"month":"2011-10-31","total_receipts":25980.0,"liquor_receipts":20094.0,"wine_receipts":1835.0,"beer_receipts":4051.0},{"month":"2011-11-30","total_receipts":21194.0,"liquor_receipts":15076.0,"wine_receipts":2036.0,"beer_receipts":4082.0},{"month":"2011-12-31","total_receipts":18531.0,"liquor_receipts":15074.0,"wine_receipts":716.0,"beer_receipts":2741.0},{"month":"2012-01-31","total_receipts":17121.0,"liquor_receipts":13444.0,"wine_receipts":758.0,"beer_receipts":2919.0},{"month":"2012-02-29","total_receipts":17627.0,"liquor_receipts":13869.0,"wine_receipts":843.0,"beer_receipts":2915.0},{"month":"2012-03-31","total_receipts":29110.0,"liquor_receipts":21340.0,"wine_receipts":1664.0,"beer_receipts":6106.0},{"month":"2012-04-30","total_receipts":23457.0,"liquor_receipts":18463.0,"wine_receipts":1275.0,"beer_receipts":3719.0},{"month":"2012-05-31","total_receipts":26022.0,"liquor_receipts":20472.0,"wine_receipts":1535.0,"beer_receipts":4015.0},{"month":"2012-06-30","total_receipts":18903.0,"liquor_receipts":14217.0,"wine_receipts":909.0,"beer_receipts":3777.0},{"month":"2012-07-31","total_receipts":20581.0,"liquor_receipts":14785.0,"wine_receipts":1649.0,"beer_receipts":4147.0},{"month":"2012-08-31","total_receipts":17485.0,"liquor_receipts":13268.0,"wine_receipts":680.0,"beer_receipts":3537.0},{"month":"2012-09-30","total_receipts":16691.0,"liquor_receipts":12583.0,"wine_receipts":1020.0,"beer_receipts":3088.0},{"month":"2012-10-31","total_receipts":16028.0,"liquor_receipts":11388.0,"wine_receipts":988.0,"beer_receipts":3652.0},{"month":"2012-11-30","total_receipts":18606.0,"liquor_receipts":13827.0,"wine_receipts":903.0,"beer_receipts":3876.0},{"month":"2012-12-31","total_receipts":12812.0,"liquor_receipts":9656.0,"wine_receipts":746.0,"beer_receipts":2410.0},{"month":"2013-01-31","total_receipts":10931.0,"liquor_receipts":7783.0,"wine_receipts":561.0,"beer_receipts":2587.0},{"month":"2013-02-28","total_receipts":14277.0,"liquor_receipts":10834.0,"wine_receipts":631.0,"beer_receipts":2812.0},{"month":"2013-03-31","total_receipts":39579.0,"liquor_receipts":28814.0,"wine_receipts":2308.0,"beer_receipts":8457.0},{"month":"2013-04-30","total_receipts":18185.0,"liquor_receipts":12808.0,"wine_receipts":1064.0,"beer_receipts":4313.0},{"month":"2013-05-31","total_receipts":23129.0,"liquor_receipts":16670.0,"wine_receipts":1087.0,"beer_receipts":5372.0},{"month":"2013-06-30","total_receipts":17787.0,"liquor_receipts":12626.0,"wine_receipts":917.0,"beer_receipts":4244.0},{"month":"2013-07-31","total_receipts":19634.0,"liquor_receipts":14232.0,"wine_receipts":883.0,"beer_receipts":4519.0},{"month":"2013-08-31","total_receipts":15315.0,"liquor_receipts":11323.0,"wine_receipts":625.0,"beer_receipts":3367.0},{"month":"2013-09-30","total_receipts":17847.0,"liquor_receipts":13492.0,"wine_receipts":813.0,"beer_receipts":3542.0},{"month":"2013-10-31","total_receipts":15466.0,"liquor_receipts":11588.0,"wine_receipts":958.0,"beer_receipts":2920.0},{"month":"2013-11-30","total_receipts":18788.0,"liquor_receipts":13637.0,"wine_receipts":1273.0,"beer_receipts":3878.0},{"month":"2013-12-31","total_receipts":8385.0,"liquor_receipts":6043.0,"wine_receipts":484.0,"beer_receipts":1858.0},{"month":"2014-01-31","total_receipts":10542.0,"liquor_receipts":7514.0,"wine_receipts":497.0,"beer_receipts":2531.0},{"month":"2014-02-28","total_receipts":14108.0,"liquor_receipts":10161.0,"wine_receipts":1031.0,"beer_receipts":2916.0},{"month":"2014-03-31","total_receipts":37947.0,"liquor_receipts":28181.0,"wine_receipts":2087.0,"beer_receipts":7679.0},{"month":"2014-04-30","total_receipts":19500.0,"liquor_receipts":13825.0,"wine_receipts":916.0,"beer_receipts":4759.0},{"month":"2014-05-31","total_receipts":19809.0,"liquor_receipts":14817.0,"wine_receipts":1515.0,"beer_receipts":3477.0},{"month":"2014-06-30","total_receipts":14060.0,"liquor_receipts":9668.0,"wine_receipts":988.0,"beer_receipts":3404.0},{"month":"2014-07-31","total_receipts":12361.0,"liquor_receipts":6885.0,"wine_receipts":1169.0,"beer_receipts":4307.0},{"month":"2014-08-31","total_receipts":13404.0,"liquor_receipts":9296.0,"wine_receipts":315.0,"beer_receipts":3793.0},{"month":"2014-09-30","total_receipts":15016.0,"liquor_receipts":11122.0,"wine_receipts":594.0,"beer_receipts":3300.0},{"month":"2014-10-31","total_receipts":12063.0,"liquor_receipts":8261.0,"wine_receipts":602.0,"beer_receipts":3200.0},{"month":"2014-11-30","total_receipts":0.0,"liquor_receipts":0.0,"wine_receipts":0.0,"beer_receipts":0.0},{"month":"2014-12-31","total_receipts":0.0,"liquor_receipts":0.0,"wine_receipts":0.0,"beer_receipts":0.0},{"month":"2015-01-31","total_receipts":0.0,"liquor_receipts":0.0,"wine_receipts":0.0,"beer_receipts":0.0},{"month":"2015-02-28","total_receipts":0.0,"liquor_receipts":0.0,"wine_receipts":0.0,"beer_receipts":0.0},{"month":"2015-03-31","total_receipts":0.0,"liquor_receipts":0.0,"wine_receipts":0.0,"beer_receipts":0.0},{"month":"2015-04-30","total_receipts":0.0,"liquor_receipts":0.0,"wine_receipts":0.0,"beer_receipts":0.0},{"month":"2015-05-31","total_receipts":0.0,"liquor_receipts":0.0,"wine_receipts":0.0,"beer_receipts":0.0},{"month":"2015-06-30","total_receipts":0.0,"liquor_receipts":0.0,"wine_receipts":0.0,"beer_receipts":0.0},{"month":"2015-07-31","total_receipts":0.0,"liquor_receipts":0.0,"wine_receipts":0.0,"beer_receipts":0.0},{"month":"2015-08-31","total_receipts":0.0,"liquor_receipts":0.0,"wine_receipts":0.0,"beer_receipts":0.0},{"month":"2015-09-30","total_receipts":0.0,"liquor_receipts":0.0,"wine_receipts":0.0,"beer_receipts":0.0},{"month":"2015-10-31","total_receipts":0.0,"liquor_receipts":0.0,"wine_receipts":0.0,"beer_receipts":0.0},{"month":"2015-11-30","total_receipts":0.0,"liquor_receipts":0.0,"wine_receipts":0.0,"beer_receipts":0.0},{"month":"2015-12-31","total_receipts":0.0,"liquor_receipts":0.0,"wine_receipts":0.0,"beer_receipts":0.0},{"month":"2016-01-31","total_receipts":0.0,"liquor_receipts":0.0,"wine_receipts":0.0,"beer_receipts":0.0},{"month":"2016-02-29","total_receipts":0.0,"liquor_receipts":0.0,"wine_receipts":0.0,"beer_receipts":0.0},{"month":"2016-03-31","total_receipts":0.0,"liquor_receipts":0.0,"wine_receipts":0.0,"beer_receipts":0.0},{"month":"2016-04-30","total_receipts":0.0,"liquor_receipts":0.0,"wine_receipts":0.0,"beer_receipts":0.0},{"month":"2016-05-31","total_receipts":0.0,"liquor_receipts":0.0,"wine_receipts":0.0,"beer_receipts":0.0},{"month":"2016-06-30","total_receipts":0.0,"liquor_receipts":0.0,"wine_receipts":0.0,"beer_receipts":0.0},{"month":"2016-07-31","total_receipts":0.0,"liquor_receipts":0.0,"wine_receipts":0.0,"beer_receipts":0.0},{"month":"2016-08-31","total_receipts":0.0,"liquor_receipts":0.0,"wine_receipts":0.0,"beer_receipts":0.0},{"month":"2016-09-30","total_receipts":0.0,"liquor_receipts":0.0,"wine_receipts":0.0,"beer_receipts":0.0},{"month":"2016-10-31","total_receipts":0.0,"liquor_receipts":0.0,"wine_receipts":0.0,"beer_receipts":0.0},{"month":"2016-11-30","total_receipts":0.0,"liquor_receipts":0.0,"wine_receipts":0.0,"beer_receipts":0.0},{"month":"2016-12-31","total_receipts":0.0,"liquor_receipts":0.0,"wine_receipts":0.0,"beer_receipts":0.0},{"month":"2017-01-31","total_receipts":0.0,"liquor_receipts":0.0,"wine_receipts":0.0,"beer_receipts":0.0},{"month":"2017-02-28","total_receipts":0.0,"liquor_receipts":0.0,"wine_receipts":0.0,"beer_receipts":0.0},{"month":"2017-03-31","total_receipts":0.0,"liquor_receipts":0.0,"wine_receipts":0.0,"beer_receipts":0.0},{"month":"2017-04-30","total_receipts":0.0,"liquor_receipts":0.0,"wine_receipts":0.0,"beer_receipts":0.0},{"month":"2017-05-31","total_receipts":0.0,"liquor_receipts":0.0,"wine_receipts":0.0,"beer_receipts":0.0},{"month":"2017-06-30","total_receipts":0.0,"liquor_receipts":0.0,"wine_receipts":0.0,"beer_receipts":0.0},{"month":"2017-07-31","total_receipts":0.0,"liquor_receipts":0.0,"wine_receipts":0.0,"beer_receipts":0.0},{"month":"2017-08-31","total_receipts":0.0,"liquor_receipts":0.0,"wine_receipts":0.0,"beer_receipts":0.0},{"month":"2017-09-30","total_receipts":0.0,"liquor_receipts":0.0,"wine_receipts":0.0,"beer_receipts":0.0},{"month":"2017-10-31","total_receipts":0.0,"liquor_receipts":0.0,"wine_receipts":0.0,"beer_receipts":0.0},{"month":"2017-11-30","total_receipts":0.0,"liquor_receipts":0.0,"wine_receipts":0.0,"beer_receipts":0.0},{"month":"2017-12-31","total_receipts":0.0,"liquor_receipts":0.0,"wine_receipts":0.0,"beer_receipts":0.0},{"month":"2018-01-31","total_receipts":0.0,"liquor_receipts":0.0,"wine_receipts":0.0,"beer_receipts":0.0},{"month":"2018-02-28","total_receipts":0.0,"liquor_receipts":0.0,"wine_receipts":0.0,"beer_receipts":0.0},{"month":"2018-03-31","total_receipts":0.0,"liquor_receipts":0.0,"wine_receipts":0.0,"beer_receipts":0.0},{"month":"2018-04-30","total_receipts":0.0,"liquor_receipts":0.0,"wine_receipts":0.0,"beer_receipts":0.0},{"month":"2018-05-31","total_receipts":0.0,"liquor_receipts":0.0,"wine_receipts":0.0,"beer_receipts":0.0},{"month":"2018-06-30","total_receipts":0.0,"liquor_receipts":0.0,"wine_receipts":0.0,"beer_receipts":0.0},{"month":"2018-07-31","total_receipts":0.0,"liquor_receipts":0.0,"wine_receipts":0.0,"beer_receipts":0.0},{"month":"2018-08-31","total_receipts":0.0,"liquor_receipts":0.0,"wine_receipts":0.0,"beer_receipts":0.0},{"month":"2018-09-30","total_receipts":0.0,"liquor_receipts":0.0,"wine_receipts":0.0,"beer_receipts":0.0},{"month":"2018-10-31","total_receipts":0.0,"liquor_receipts":0.0,"wine_receipts":0.0,"beer_receipts":0.0},{"month":"2018-11-30","total_receipts":0.0,"liquor_receipts":0.0,"wine_receipts":0.0,"beer_receipts":0.0},{"month":"2018-12-31","total_receipts":0.0,"liquor_receipts":0.0,"wine_receipts":0.0,"beer_receipts":0.0},{"month":"2019-01-31","total_receipts":0.0,"liquor_receipts":0.0,"wine_receipts":0.0,"beer_receipts":0.0},{"month":"2019-02-28","total_receipts":0.0,"liquor_receipts":0.0,"wine_receipts":0.0,"beer_receipts":0.0},{"month":"2019-03-31","total_receipts":0.0,"liquor_receipts":0.0,"wine_receipts":0.0,"beer_receipts":0.0},{"month":"2019-04-30","total_receipts":0.0,"liquor_receipts":0.0,"wine_receipts":0.0,"beer_receipts":0.0},{"month":"2019-05-31","total_receipts":0.0,"liquor_receipts":0.0,"wine_receipts":0.0,"beer_receipts":0.0},{"month":"2019-06-30","total_receipts":0.0,"liquor_receipts":0.0,"wine_receipts":0.0,"beer_receipts":0.0},{"month":"2019-07-31","total_receipts":0.0,"liquor_receipts":0.0,"wine_receipts":0.0,"beer_receipts":0.0},{"month":"2019-08-31","total_receipts":0.0,"liquor_receipts":0.0,"wine_receipts":0.0,"beer_receipts":0.0},{"month":"2019-09-30","total_receipts":0.0,"liquor_receipts":0.0,"wine_receipts":0.0,"beer_receipts":0.0},{"month":"2019-10-31","total_receipts":0.0,"liquor_receipts":0.0,"wine_receipts":0.0,"beer_receipts":0.0},{"month":"2019-11-30","total_receipts":0.0,"liquor_receipts":0.0,"wine_receipts":0.0,"beer_receipts":0.0},{"month":"2019-12-31","total_receipts":0.0,"liquor_receipts":0.0,"wine_receipts":0.0,"beer_receipts":0.0},{"month":"2020-01-31","total_receipts":0.0,"liquor_receipts":0.0,"wine_receipts":0.0,"beer_receipts":0.0},{"month":"2020-02-29","total_receipts":0.0,"liquor_receipts":0.0,"wine_receipts":0.0,"beer_receipts":0.0},{"month":"2020-03-31","total_receipts":0.0,"liquor_receipts":0.0,"wine_receipts":0.0,"beer_receipts":0.0},{"month":"2020-04-30","total_receipts":0.0,"liquor_receipts":0.0,"wine_receipts":0.0,"beer_receipts":0.0},{"month":"2020-05-31","total_receipts":0.0,"liquor_receipts":0.0,"wine_receipts":0.0,"beer_receipts":0.0},{"month":"2020-06-30","total_receipts":0.0,"liquor_receipts":0.0,"wine_receipts":0.0,"beer_receipts":0.0},{"month":"2020-07-31","total_receipts":0.0,"liquor_receipts":0.0,"wine_receipts":0.0,"beer_receipts":0.0},{"month":"2020-08-31","total_receipts":0.0,"liquor_receipts":0.0,"wine_receipts":0.0,"beer_receipts":0.0},{"month":"2020-09-30","total_receipts":0.0,"liquor_receipts":0.0,"wine_receipts":0.0,"beer_receipts":0.0},{"month":"2020-10-31","total_receipts":0.0,"liquor_receipts":0.0,"wine_receipts":0.0,"beer_receipts":0.0},{"month":"2020-11-30","total_receipts":0.0,"liquor_receipts":0.0,"wine_receipts":0.0,"beer_receipts":0.0},{"month":"2020-12-31","total_receipts":0.0,"liquor_receipts":0.0,"wine_receipts":0.0,"beer_receipts":0.0},{"month":"2021-01-31","total_receipts":0.0,"liquor_receipts":0.0,"wine_receipts":0.0,"beer_receipts":0.0},{"month":"2021-02-28","total_receipts":0.0,"liquor_receipts":0.0,"wine_receipts":0.0,"beer_receipts":0.0},{"month":"2021-03-31","total_receipts":0.0,"liquor_receipts":0.0,"wine_receipts":0.0,"beer_receipts":0.0},{"month":"2021-04-30","total_receipts":0.0,"liquor_receipts":0.0,"wine_receipts":0.0,"beer_receipts":0.0},{"month":"2021-05-31","total_receipts":0.0,"liquor_receipts":0.0,"wine_receipts":0.0,"beer_receipts":0.0},{"month":"2021-06-30","total_receipts":0.0,"liquor_receipts":0.0,"wine_receipts":0.0,"beer_receipts":0.0},{"month":"2021-07-31","total_receipts":0.0,"liquor_receipts":0.0,"wine_receipts":0.0,"beer_receipts":0.0},{"month":"2021-08-31","total_receipts":0.0,"liquor_receipts":0.0,"wine_receipts":0.0,"beer_receipts":0.0},{"month":"2021-09-30","total_receipts":0.0,"liquor_receipts":0.0,"wine_receipts":0.0,"beer_receipts":0.0},{"month":"2021-10-31","total_receipts":0.0,"liquor_receipts":0.0,"wine_receipts":0.0,"beer_receipts":0.0},{"month":"2021-11-30","total_receipts":0.0,"liquor_receipts":0.0,"wine_receipts":0.0,"beer_receipts":0.0},{"month":"2021-12-31","total_receipts":0.0,"liquor_receipts":0.0,"wine_receipts":0.0,"beer_receipts":0.0},{"month":"2022-01-31","total_receipts":0.0,"liquor_receipts":0.0,"wine_receipts":0.0,"beer_receipts":0.0},{"month":"2022-02-28","total_receipts":0.0,"liquor_receipts":0.0,"wine_receipts":0.0,"beer_receipts":0.0},{"month":"2022-03-31","total_receipts":0.0,"liquor_receipts":0.0,"wine_receipts":0.0,"beer_receipts":0.0},{"month":"2022-04-30","total_receipts":0.0,"liquor_receipts":0.0,"wine_receipts":0.0,"beer_receipts":0.0},{"month":"2022-05-31","total_receipts":0.0,"liquor_receipts":0.0,"wine_receipts":0.0,"beer_receipts":0.0},{"month":"2022-06-30","total_receipts":0.0,"liquor_receipts":0.0,"wine_receipts":0.0,"beer_receipts":0.0},{"month":"2022-07-31","total_receipts":0.0,"liquor_receipts":0.0,"wine_receipts":0.0,"beer_receipts":0.0},{"month":"2022-08-31","total_receipts":0.0,"liquor_receipts":0.0,"wine_receipts":0.0,"beer_receipts":0.0},{"month":"2022-09-30","total_receipts":0.0,"liquor_receipts":0.0,"wine_receipts":0.0,"beer_receipts":0.0},{"month":"2022-10-31","total_receipts":0.0,"liquor_receipts":0.0,"wine_receipts":0.0,"beer_receipts":0.0},{"month":"2022-11-30","total_receipts":0.0,"liquor_receipts":0.0,"wine_receipts":0.0,"beer_receipts":0.0},{"month":"2022-12-31","total_receipts":0.0,"liquor_receipts":0.0,"wine_receipts":0.0,"beer_receipts":0.0},{"month":"2023-01-31","total_receipts":0.0,"liquor_receipts":0.0,"wine_receipts":0.0,"beer_receipts":0.0},{"month":"2023-02-28","total_receipts":0.0,"liquor_receipts":0.0,"wine_receipts":0.0,"beer_receipts":0.0},{"month":"2023-03-31","total_receipts":0.0,"liquor_receipts":0.0,"wine_receipts":0.0,"beer_receipts":0.0},{"month":"2023-04-30","total_receipts":0.0,"liquor_receipts":0.0,"wine_receipts":0.0,"beer_receipts":0.0},{"month":"2023-05-31","total_receipts":0.0,"liquor_receipts":0.0,"wine_receipts":0.0,"beer_receipts":0.0},{"month":"2023-06-30","total_receipts":0.0,"liquor_receipts":0.0,"wine_receipts":0.0,"beer_receipts":0.0},{"month":"2023-07-31","total_receipts":0.0,"liquor_receipts":0.0,"wine_receipts":0.0,"beer_receipts":0.0},{"month":"2023-08-31","total_receipts":0.0,"liquor_receipts":0.0,"wine_receipts":0.0,"beer_receipts":0.0},{"month":"2023-09-30","total_receipts":0.0,"liquor_receipts":0.0,"wine_receipts":0.0,"beer_receipts":0.0},{"month":"2023-10-31","total_receipts":0.0,"liquor_receipts":0.0,"wine_receipts":0.0,"beer_receipts":0.0},{"month":"2023-11-30","total_receipts":0.0,"liquor_receipts":0.0,"wine_receipts":0.0,"beer_receipts":0.0},{"month":"2023-12-31","total_receipts":0.0,"liquor_receipts":0.0,"wine_receipts":0.0,"beer_receipts":0.0},{"month":"2024-01-31","total_receipts":0.0,"liquor_receipts":0.0,"wine_receipts":0.0,"beer_receipts":0.0},{"month":"2024-02-29","total_receipts":0.0,"liquor_receipts":0.0,"wine_receipts":0.0,"beer_receipts":0.0},{"month":"2024-03-31","total_receipts":0.0,"liquor_receipts":0.0,"wine_receipts":0.0,"beer_receipts":0.0},{"month":"2024-04-30","total_receipts":0.0,"liquor_receipts":0.0,"wine_receipts":0.0,"beer_receipts":0.0},{"month":"2024-05-31","total_receipts":0.0,"liquor_receipts":0.0,"wine_receipts":0.0,"beer_receipts":0.0},{"month":"2024-06-30","total_receipts":0.0,"liquor_receipts":0.0,"wine_receipts":0.0,"beer_receipts":0.0},{"month":"2024-07-31","total_receipts":0.0,"liquor_receipts":0.0,"wine_receipts":0.0,"beer_receipts":0.0},{"month":"2024-08-31","total_receipts":0.0,"liquor_receipts":0.0,"wine_receipts":0.0,"beer_receipts":0.0},{"month":"2024-09-30","total_receipts":0.0,"liquor_receipts":0.0,"wine_receipts":0.0,"beer_receipts":0.0},{"month":"2024-10-31","total_receipts":0.0,"liquor_receipts":0.0,"wine_receipts":0.0,"beer_receipts":0.0},{"month":"2024-11-30","total_receipts":0.0,"liquor_receipts":0.0,"wine_receipts":0.0,"beer_receipts":0.0},{"month":"2024-12-31","total_receipts":0.0,"liquor_receipts":0.0,"wine_receipts":0.0,"beer_receipts":0.0},{"month":"2025-01-31","total_receipts":0.0,"liquor_receipts":0.0,"wine_receipts":0.0,"beer_receipts":0.0},{"month":"2025-02-28","total_receipts":0.0,"liquor_receipts":0.0,"wine_receipts":0.0,"beer_receipts":0.0},{"month":"2025-03-31","total_receipts":0.0,"liquor_receipts":0.0,"wine_receipts":0.0,"beer_receipts":0.0},{"month":"2025-04-30","total_receipts":0.0,"liquor_receipts":0.0,"wine_receipts":0.0,"beer_receipts":0.0},{"month":"2025-05-31","total_receipts":0.0,"liquor_receipts":0.0,"wine_receipts":0.0,"beer_receipts":0.0},{"month":"2025-06-30","total_receipts":0.0,"liquor_receipts":0.0,"wine_receipts":0.0,"beer_receipts":0.0},{"month":"2025-07-31","total_receipts":0.0,"liquor_receipts":0.0,"wine_receipts":0.0,"beer_receipts":0.0},{"month":"2025-08-31","total_receipts":0.0,"liquor_receipts":0.0,"wine_receipts":0.0,"beer_receipts":0.0},{"month":"2025-09-30","total_receipts":0.0,"liquor_receipts":0.0,"wine_receipts":0.0,"beer_receipts":0.0},{"month":"2025-10-31","total_receipts":0.0,"liquor_receipts":0.0,"wine_receipts":0.0,"beer_receipts":0.0},{"month":"2025-11-30","total_receipts":0.0,"liquor_receipts":0.0,"wine_receipts":0.0,"beer_receipts":0.0},{"month":"2025-12-31","total_receipts":0.0,"liquor_receipts":0.0,"wine_receipts":0.0,"beer_receipts":0.0},{"month":"2026-01-31","total_receipts":0.0,"liquor_receipts":0.0,"wine_receipts":0.0,"beer_receipts":0.0},{"month":"2026-02-28","total_receipts":0.0,"liquor_receipts":0.0,"wine_receipts":0.0,"beer_receipts":0.0},{"month":"2026-03-31","total_receipts":0.0,"liquor_receipts":0.0,"wine_receipts":0.0,"beer_receipts":0.0}],"violations":[]}