{"zips":[{"city":"AUSTIN","zip":"78617","establishments":1,"avg_score":91.75,"total_receipts":0.0,"latitude":30.1745,"longitude":-97.6134},{"city":"AUSTIN","zip":"78660","establishments":1,"avg_score":93.03,"total_receipts":3322378.0,"latitude":30.4421,"longitude":-97.6299},{"city":"AUSTIN","zip":"78701","establishments":379,"avg_score":88.48,"total_receipts":1077774923.0,"latitude":30.2713,"longitude":-97.7426},{"city":"AUSTIN","zip":"78702","establishments":185,"avg_score":89.56,"total_receipts":327466772.0,"latitude":30.2638,"longitude":-97.7166},{"city":"AUSTIN","zip":"78703","establishments":50,"avg_score":90.18,"total_receipts":114725262.0,"latitude":30.2907,"longitude":-97.7648},{"city":"AUSTIN","zip":"78704","establishments":177,"avg_score":90.82,"total_receipts":388183853.0,"latitude":30.2428,"longitude":-97.7658},{"city":"AUSTIN","zip":"78705","establishments":52,"avg_score":89.62,"total_receipts":51274610.0,"latitude":30.2896,"longitude":-97.7396},{"city":"AUSTIN","zip":"78712","establishments":7,"avg_score":0.0,"total_receipts":48326271.0,"latitude":30.2852,"longitude":-97.7354},{"city":"AUSTIN","zip":"78713","establishments":1,"avg_score":0.0,"total_receipts":308643.0,"latitude":30.2672,"longitude":-97.7431},{"city":"AUSTIN","zip":"78717","establishments":31,"avg_score":91.43,"total_receipts":31583351.0,"latitude":30.506,"longitude":-97.7472},{"city":"AUSTIN","zip":"78719","establishments":25,"avg_score":90.88,"total_receipts":73119672.0,"latitude":30.1802,"longitude":-97.6667},{"city":"AUSTIN","zip":"78721","establishments":4,"avg_score":92.3,"total_receipts":2885318.0,"latitude":30.2721,"longitude":-97.6868},{"city":"AUSTIN","zip":"78722","establishments":23,"avg_score":90.2,"total_receipts":35813233.0,"latitude":30.2893,"longitude":-97.715},{"city":"AUSTIN","zip":"78723","establishments":39,"avg_score":90.16,"total_receipts":34565826.0,"latitude":30.3085,"longitude":-97.6849},{"city":"AUSTIN","zip":"78724","establishments":8,"avg_score":91.06,"total_receipts":5084384.0,"latitude":30.296,"longitude":-97.6396},{"city":"AUSTIN","zip":"78726","establishments":17,"avg_score":94.11,"total_receipts":13731566.0,"latitude":30.43,"longitude":-97.8326},{"city":"AUSTIN","zip":"78727","establishments":13,"avg_score":91.04,"total_receipts":6057595.0,"latitude":30.4254,"longitude":-97.7195},{"city":"AUSTIN","zip":"78728","establishments":13,"avg_score":92.9,"total_receipts":31202394.0,"latitude":30.4417,"longitude":-97.6811},{"city":"AUSTIN","zip":"78729","establishments":14,"avg_score":92.72,"total_receipts":18151301.0,"latitude":30.4521,"longitude":-97.7688},{"city":"AUSTIN","zip":"78730","establishments":7,"avg_score":91.17,"total_receipts":9339486.0,"latitude":30.3607,"longitude":-97.8241},{"city":"AUSTIN","zip":"78731","establishments":28,"avg_score":91.24,"total_receipts":29647517.0,"latitude":30.3471,"longitude":-97.7609},{"city":"AUSTIN","zip":"78732","establishments":12,"avg_score":94.01,"total_receipts":31419315.0,"latitude":30.3752,"longitude":-97.9007},{"city":"AUSTIN","zip":"78733","establishments":2,"avg_score":93.38,"total_receipts":2088988.0,"latitude":30.3314,"longitude":-97.8666},{"city":"AUSTIN","zip":"78734","establishments":16,"avg_score":90.14,"total_receipts":5705281.0,"latitude":30.3705,"longitude":-97.9427},{"city":"AUSTIN","zip":"78735","establishments":26,"avg_score":91.56,"total_receipts":67423852.0,"latitude":30.249,"longitude":-97.8414},{"city":"AUSTIN","zip":"78736","establishments":14,"avg_score":92.18,"total_receipts":4933080.0,"latitude":30.2444,"longitude":-97.916},{"city":"AUSTIN","zip":"78737","establishments":23,"avg_score":91.83,"total_receipts":11303561.0,"latitude":30.2107,"longitude":-97.9427},{"city":"AUSTIN","zip":"78738","establishments":7,"avg_score":92.91,"total_receipts":4229320.0,"latitude":30.3337,"longitude":-97.9824},{"city":"AUSTIN","zip":"78739","establishments":2,"avg_score":97.71,"total_receipts":1910489.0,"latitude":30.172,"longitude":-97.8784},{"city":"AUSTIN","zip":"78741","establishments":42,"avg_score":90.05,"total_receipts":63781752.0,"latitude":30.2315,"longitude":-97.7223},{"city":"AUSTIN","zip":"78742","establishments":5,"avg_score":96.2,"total_receipts":178348.0,"latitude":30.2313,"longitude":-97.6703},{"city":"AUSTIN","zip":"78744","establishments":36,"avg_score":91.71,"total_receipts":20547312.0,"latitude":30.1876,"longitude":-97.7472},{"city":"AUSTIN","zip":"78745","establishments":56,"avg_score":89.8,"total_receipts":64306234.0,"latitude":30.2063,"longitude":-97.7956},{"city":"AUSTIN","zip":"78746","establishments":24,"avg_score":92.72,"total_receipts":31763387.0,"latitude":30.2971,"longitude":-97.8181},{"city":"AUSTIN","zip":"78747","establishments":4,"avg_score":90.9,"total_receipts":3102903.0,"latitude":30.1204,"longitude":-97.7433},{"city":"AUSTIN","zip":"78748","establishments":57,"avg_score":91.73,"total_receipts":81672932.0,"latitude":30.1743,"longitude":-97.8225},{"city":"AUSTIN","zip":"78749","establishments":24,"avg_score":93.71,"total_receipts":31672254.0,"latitude":30.2166,"longitude":-97.8508},{"city":"AUSTIN","zip":"78750","establishments":43,"avg_score":90.88,"total_receipts":27255311.0,"latitude":30.4224,"longitude":-97.7967},{"city":"AUSTIN","zip":"78751","establishments":38,"avg_score":91.08,"total_receipts":42003347.0,"latitude":30.3093,"longitude":-97.7242},{"city":"AUSTIN","zip":"78752","establishments":49,"avg_score":89.84,"total_receipts":74103579.0,"latitude":30.3316,"longitude":-97.7004},{"city":"AUSTIN","zip":"78753","establishments":70,"avg_score":89.95,"total_receipts":39394751.0,"latitude":30.3649,"longitude":-97.6827},{"city":"AUSTIN","zip":"78754","establishments":12,"avg_score":92.68,"total_receipts":4871852.0,"latitude":30.3423,"longitude":-97.6673},{"city":"AUSTIN","zip":"78756","establishments":30,"avg_score":91.95,"total_receipts":32887690.0,"latitude":30.3223,"longitude":-97.739},{"city":"AUSTIN","zip":"78757","establishments":48,"avg_score":92.02,"total_receipts":59531171.0,"latitude":30.3437,"longitude":-97.7316},{"city":"AUSTIN","zip":"78758","establishments":104,"avg_score":92.33,"total_receipts":238037101.0,"latitude":30.3764,"longitude":-97.7078},{"city":"AUSTIN","zip":"78759","establishments":58,"avg_score":91.38,"total_receipts":73098548.0,"latitude":30.4036,"longitude":-97.7526},{"city":"AUSTIN","zip":"78774","establishments":1,"avg_score":0.0,"total_receipts":50728.0,"latitude":30.3264,"longitude":-97.7713},{"city":"AUSTIN","zip":"78652","establishments":0,"avg_score":94.43,"total_receipts":0.0,"latitude":30.1238,"longitude":-97.8393},{"city":"AUSTIN","zip":"78612","establishments":0,"avg_score":81.0,"total_receipts":0.0,"latitude":30.0966,"longitude":-97.4976},{"city":"AUSTIN","zip":"78664","establishments":0,"avg_score":94.12,"total_receipts":0.0,"latitude":30.5145,"longitude":-97.668},{"city":"AUSTIN","zip":"78620","establishments":0,"avg_score":94.81,"total_receipts":0.0,"latitude":30.2268,"longitude":-98.1029},{"city":"AUSTIN","zip":"78613","establishments":0,"avg_score":90.2,"total_receipts":0.0,"latitude":30.5052,"longitude":-97.8203},{"city":"AUSTIN","zip":"78634","establishments":0,"avg_score":93.5,"total_receipts":0.0,"latitude":30.5257,"longitude":-97.5672},{"city":"AUSTIN","zip":"78621","establishments":0,"avg_score":90.8,"total_receipts":0.0,"latitude":30.3231,"longitude":-97.3737},{"city":"AUSTIN","zip":"78669","establishments":0,"avg_score":93.53,"total_receipts":0.0,"latitude":30.3899,"longitude":-98.0539},{"city":"AUSTIN","zip":"78610","establishments":0,"avg_score":97.57,"total_receipts":0.0,"latitude":30.0918,"longitude":-97.8534},{"city":"AUSTIN","zip":"78615","establishments":0,"avg_score":83.25,"total_receipts":0.0,"latitude":30.4872,"longitude":-97.3676},{"city":"AUSTIN","zip":"78653","establishments":0,"avg_score":90.69,"total_receipts":0.0,"latitude":30.3388,"longitude":-97.5323},{"city":"AUSTIN","zip":"78725","establishments":0,"avg_score":97.19,"total_receipts":0.0,"latitude":30.2562,"longitude":-97.6243},{"city":"AUSTIN","zip":"78641","establishments":0,"avg_score":86.0,"total_receipts":0.0,"latitude":30.5835,"longitude":-97.8575},{"city":"AUSTIN","zip":"78654","establishments":0,"avg_score":87.0,"total_receipts":0.0,"latitude":30.5784,"longitude":-98.2751}]}